fastapi_okta/__init__.py
fastapi_okta/auth_okta.py
fastapi_okta/okta_utils.py
fastapi_okta/py.typed
fastapi_okta-1.4.0.dist-info/LICENSE
fastapi_okta-1.4.0.dist-info/METADATA
fastapi_okta-1.4.0.dist-info/WHEEL
fastapi_okta-1.4.0.dist-info/top_level.txt
fastapi_okta-1.4.0.dist-info/RECORD
