Metadata-Version: 2.1
Name: fastapi-okta
Version: 1.4.0
Summary: Easy Okta integration for FastAPI
Author: Alliance Blue Team
License: MIT
Project-URL: Homepage, https://github.com/alliance-genome/agr_fastapi_okta
Project-URL: Repository, https://github.com/alliance-genome/agr_fastapi_okta
Project-URL: Issues, https://github.com/alliance-genome/agr_fastapi_okta/issues
Classifier: Development Status :: 4 - Beta
Classifier: Intended Audience :: Developers
Classifier: License :: OSI Approved :: MIT License
Classifier: Programming Language :: Python :: 3
Classifier: Programming Language :: Python :: 3.8
Classifier: Programming Language :: Python :: 3.9
Classifier: Programming Language :: Python :: 3.10
Classifier: Programming Language :: Python :: 3.11
Classifier: Programming Language :: Python :: 3.12
Classifier: Topic :: Software Development :: Libraries :: Python Modules
Classifier: Framework :: FastAPI
Requires-Python: >=3.8
License-File: LICENSE
Requires-Dist: fastapi>=0.95.2
Requires-Dist: python-jose>=3.4.0
